noble/__init__.py
noble-0.0.1.dist-info/LICENSE
noble-0.0.1.dist-info/WHEEL
noble-0.0.1.dist-info/METADATA
noble-0.0.1.dist-info/RECORD
