Metadata-Version: 2.1
Name: noble
Version: 0.0.1
Summary: Fast (indexed) bazel queries
License: MIT
Author: Timothy Crosley
Author-email: timothy.crosley@gmail.com
Requires-Python: >=3.7
Classifier: License :: OSI Approved :: MIT License
Classifier: Programming Language :: Python :: 3
Classifier: Programming Language :: Python :: 3.7
Classifier: Programming Language :: Python :: 3.8
Classifier: Programming Language :: Python :: 3.9
Classifier: Programming Language :: Python :: 3.10
Classifier: Programming Language :: Python :: 3.11
